bulk_file_renamer/__init__.py
bulk_file_renamer/bulk_file_renamer.py
BFR-0.11.dist-info/LICENSE
BFR-0.11.dist-info/METADATA
BFR-0.11.dist-info/WHEEL
BFR-0.11.dist-info/top_level.txt
BFR-0.11.dist-info/RECORD
